UserAgenter/__init__.py
UserAgenter/user_agent.py
UserAgenter/utils.py
UserAgenter-1.3.1.dist-info/METADATA
UserAgenter-1.3.1.dist-info/WHEEL
UserAgenter-1.3.1.dist-info/top_level.txt
UserAgenter-1.3.1.dist-info/RECORD
